tair_gdn_latency_test/__init__.py
tair_gdn_latency_test/cli.py
tair_gdn_latency_test/reader.py
tair_gdn_latency_test/writer.py
tairgdn_latencytest-0.0.2.dist-info/licenses/LICENSE
tairgdn_latencytest-0.0.2.dist-info/METADATA
tairgdn_latencytest-0.0.2.dist-info/WHEEL
tairgdn_latencytest-0.0.2.dist-info/entry_points.txt
tairgdn_latencytest-0.0.2.dist-info/top_level.txt
tairgdn_latencytest-0.0.2.dist-info/RECORD
