Metadata-Version: 2.4
Name: tairgdn-latencytest
Version: 0.0.2
Summary: A tool to test Tair GDN sync latency.
Requires-Python: >=3.9
License-File: LICENSE
Requires-Dist: redis>=4.2.0
Requires-Dist: numpy
Requires-Dist: rich>=13.0.0
Requires-Dist: matplotlib>=3.7.0
Dynamic: license-file
